[
  {
    "inputs": [
      {
        "internalType": "address",
        "name": "_certificationManager",
        "type": "address"
      }
    ],
    "stateMutability": "nonpayable",
    "type": "constructor"
  },
  {
    "anonymous": false,
    "inputs": [
      {
        "indexed": false,
        "internalType": "uint256",
        "name": "amount",
        "type": "uint256"
      }
    ],
    "name": "FundsAdded",
    "type": "event"
  },
  {
    "anonymous": false,
    "inputs": [
      {
        "indexed": false,
        "internalType": "uint256",
        "name": "amount",
        "type": "uint256"
      }
    ],
    "name": "FundsWithdrawn",
    "type": "event"
  },
  {
    "anonymous": false,
    "inputs": [
      {
        "indexed": true,
        "internalType": "uint256",
        "name": "loanId",
        "type": "uint256"
      }
    ],
    "name": "LoanApproved",
    "type": "event"
  },
  {
    "anonymous": false,
    "inputs": [
      {
        "indexed": true,
        "internalType": "uint256",
        "name": "loanId",
        "type": "uint256"
      }
    ],
    "name": "LoanDefaulted",
    "type": "event"
  },
  {
    "anonymous": false,
    "inputs": [
      {
        "indexed": true,
        "internalType": "uint256",
        "name": "loanId",
        "type": "uint256"
      },
      {
        "indexed": true,
        "internalType": "address",
        "name": "borrower",
        "type": "address"
      },
      {
        "indexed": true,
        "internalType": "uint256",
        "name": "tierId",
        "type": "uint256"
      },
      {
        "indexed": false,
        "internalType": "uint256",
        "name": "amount",
        "type": "uint256"
      }
    ],
    "name": "LoanRequested",
    "type": "event"
  },
  {
    "anonymous": false,
    "inputs": [
      {
        "indexed": true,
        "internalType": "uint256",
        "name": "loanId",
        "type": "uint256"
      },
      {
        "indexed": false,
        "internalType": "uint256",
        "name": "amount",
        "type": "uint256"
      }
    ],
    "name": "LoanRepayment",
    "type": "event"
  },
  {
    "anonymous": false,
    "inputs": [
      {
        "indexed": true,
        "internalType": "uint256",
        "name": "loanId",
        "type": "uint256"
      },
      {
        "indexed": false,
        "internalType": "string",
        "name": "reason",
        "type": "string"
      }
    ],
    "name": "LoanRejected",
    "type": "event"
  },
  {
    "anonymous": false,
    "inputs": [
      {
        "indexed": true,
        "internalType": "uint256",
        "name": "tierId",
        "type": "uint256"
      },
      {
        "indexed": false,
        "internalType": "string",
        "name": "name",
        "type": "string"
      },
      {
        "indexed": false,
        "internalType": "uint256",
        "name": "minScore",
        "type": "uint256"
      },
      {
        "indexed": false,
        "internalType": "uint256",
        "name": "maxAmount",
        "type": "uint256"
      },
      {
        "indexed": false,
        "internalType": "uint256",
        "name": "interestRate",
        "type": "uint256"
      },
      {
        "indexed": false,
        "internalType": "uint256",
        "name": "termMonths",
        "type": "uint256"
      }
    ],
    "name": "LoanTierCreated",
    "type": "event"
  },
  {
    "anonymous": false,
    "inputs": [
      {
        "indexed": true,
        "internalType": "uint256",
        "name": "tierId",
        "type": "uint256"
      },
      {
        "indexed": false,
        "internalType": "string",
        "name": "name",
        "type": "string"
      },
      {
        "indexed": false,
        "internalType": "uint256",
        "name": "minScore",
        "type": "uint256"
      },
      {
        "indexed": false,
        "internalType": "uint256",
        "name": "maxAmount",
        "type": "uint256"
      },
      {
        "indexed": false,
        "internalType": "uint256",
        "name": "interestRate",
        "type": "uint256"
      },
      {
        "indexed": false,
        "internalType": "uint256",
        "name": "termMonths",
        "type": "uint256"
      },
      {
        "indexed": false,
        "internalType": "bool",
        "name": "active",
        "type": "bool"
      }
    ],
    "name": "LoanTierUpdated",
    "type": "event"
  },
  {
    "anonymous": false,
    "inputs": [
      {
        "indexed": true,
        "internalType": "address",
        "name": "previousOwner",
        "type": "address"
      },
      {
        "indexed": true,
        "internalType": "address",
        "name": "newOwner",
        "type": "address"
      }
    ],
    "name": "OwnershipTransferred",
    "type": "event"
  },
  {
    "inputs": [],
    "name": "addFunds",
    "outputs": [],
    "stateMutability": "payable",
    "type": "function"
  },
  {
    "inputs": [
      {
        "internalType": "uint256",
        "name": "loanId",
        "type": "uint256"
      }
    ],
    "name": "approveLoan",
    "outputs": [],
    "stateMutability": "nonpayable",
    "type": "function"
  },
  {
    "inputs": [
      {
        "internalType": "address",
        "name": "",
        "type": "address"
      },
      {
        "internalType": "uint256",
        "name": "",
        "type": "uint256"
      }
    ],
    "name": "borrowerLoans",
    "outputs": [
      {
        "internalType": "uint256",
        "name": "",
        "type": "uint256"
      }
    ],
    "stateMutability": "view",
    "type": "function"
  },
  {
    "inputs": [
      {
        "internalType": "uint256",
        "name": "loanId",
        "type": "uint256"
      }
    ],
    "name": "calculateTotalDue",
    "outputs": [
      {
        "internalType": "uint256",
        "name": "",
        "type": "uint256"
      }
    ],
    "stateMutability": "view",
    "type": "function"
  },
  {
    "inputs": [],
    "name": "certificationManager",
    "outputs": [
      {
        "internalType": "contract ICertificationManager",
        "name": "",
        "type": "address"
      }
    ],
    "stateMutability": "view",
    "type": "function"
  },
  {
    "inputs": [
      {
        "internalType": "string",
        "name": "name",
        "type": "string"
      },
      {
        "internalType": "uint256",
        "name": "minScore",
        "type": "uint256"
      },
      {
        "internalType": "uint256",
        "name": "maxAmount",
        "type": "uint256"
      },
      {
        "internalType": "uint256",
        "name": "interestRate",
        "type": "uint256"
      },
      {
        "internalType": "uint256",
        "name": "termMonths",
        "type": "uint256"
      }
    ],
    "name": "createLoanTier",
    "outputs": [],
    "stateMutability": "nonpayable",
    "type": "function"
  },
  {
    "inputs": [
      {
        "internalType": "address",
        "name": "borrower",
        "type": "address"
      }
    ],
    "name": "getBorrowerLoans",
    "outputs": [
      {
        "components": [
          {
            "internalType": "uint256",
            "name": "id",
            "type": "uint256"
          },
          {
            "internalType": "address",
            "name": "borrower",
            "type": "address"
          },
          {
            "internalType": "uint256",
            "name": "tierId",
            "type": "uint256"
          },
          {
            "internalType": "uint256",
            "name": "amount",
            "type": "uint256"
          },
          {
            "internalType": "uint256",
            "name": "interestRate",
            "type": "uint256"
          },
          {
            "internalType": "uint256",
            "name": "termMonths",
            "type": "uint256"
          },
          {
            "internalType": "uint256",
            "name": "startDate",
            "type": "uint256"
          },
          {
            "internalType": "uint256",
            "name": "endDate",
            "type": "uint256"
          },
          {
            "internalType": "uint256",
            "name": "totalRepaid",
            "type": "uint256"
          },
          {
            "internalType": "bool",
            "name": "active",
            "type": "bool"
          },
          {
            "internalType": "bool",
            "name": "defaulted",
            "type": "bool"
          }
        ],
        "internalType": "struct LoanManager.Loan[]",
        "name": "",
        "type": "tuple[]"
      }
    ],
    "stateMutability": "view",
    "type": "function"
  },
  {
    "inputs": [
      {
        "internalType": "address",
        "name": "borrower",
        "type": "address"
      }
    ],
    "name": "getEligibleLoanTiers",
    "outputs": [
      {
        "internalType": "uint256[]",
        "name": "",
        "type": "uint256[]"
      }
    ],
    "stateMutability": "view",
    "type": "function"
  },
  {
    "inputs": [
      {
        "internalType": "uint256",
        "name": "loanId",
        "type": "uint256"
      }
    ],
    "name": "getMonthlyPayment",
    "outputs": [
      {
        "internalType": "uint256",
        "name": "",
        "type": "uint256"
      }
    ],
    "stateMutability": "view",
    "type": "function"
  },
  {
    "inputs": [
      {
        "internalType": "address",
        "name": "borrower",
        "type": "address"
      },
      {
        "internalType": "uint256",
        "name": "tierId",
        "type": "uint256"
      }
    ],
    "name": "isEligibleForLoan",
    "outputs": [
      {
        "internalType": "bool",
        "name": "",
        "type": "bool"
      }
    ],
    "stateMutability": "view",
    "type": "function"
  },
  {
    "inputs": [],
    "name": "loanCount",
    "outputs": [
      {
        "internalType": "uint256",
        "name": "",
        "type": "uint256"
      }
    ],
    "stateMutability": "view",
    "type": "function"
  },
  {
    "inputs": [
      {
        "internalType": "uint256",
        "name": "",
        "type": "uint256"
      }
    ],
    "name": "loanTiers",
    "outputs": [
      {
        "internalType": "string",
        "name": "name",
        "type": "string"
      },
      {
        "internalType": "uint256",
        "name": "minScore",
        "type": "uint256"
      },
      {
        "internalType": "uint256",
        "name": "maxAmount",
        "type": "uint256"
      },
      {
        "internalType": "uint256",
        "name": "interestRate",
        "type": "uint256"
      },
      {
        "internalType": "uint256",
        "name": "termMonths",
        "type": "uint256"
      },
      {
        "internalType": "bool",
        "name": "active",
        "type": "bool"
      }
    ],
    "stateMutability": "view",
    "type": "function"
  },
  {
    "inputs": [
      {
        "internalType": "uint256",
        "name": "",
        "type": "uint256"
      }
    ],
    "name": "loans",
    "outputs": [
      {
        "internalType": "uint256",
        "name": "id",
        "type": "uint256"
      },
      {
        "internalType": "address",
        "name": "borrower",
        "type": "address"
      },
      {
        "internalType": "uint256",
        "name": "tierId",
        "type": "uint256"
      },
      {
        "internalType": "uint256",
        "name": "amount",
        "type": "uint256"
      },
      {
        "internalType": "uint256",
        "name": "interestRate",
        "type": "uint256"
      },
      {
        "internalType": "uint256",
        "name": "termMonths",
        "type": "uint256"
      },
      {
        "internalType": "uint256",
        "name": "startDate",
        "type": "uint256"
      },
      {
        "internalType": "uint256",
        "name": "endDate",
        "type": "uint256"
      },
      {
        "internalType": "uint256",
        "name": "totalRepaid",
        "type": "uint256"
      },
      {
        "internalType": "bool",
        "name": "active",
        "type": "bool"
      },
      {
        "internalType": "bool",
        "name": "defaulted",
        "type": "bool"
      }
    ],
    "stateMutability": "view",
    "type": "function"
  },
  {
    "inputs": [
      {
        "internalType": "uint256",
        "name": "loanId",
        "type": "uint256"
      }
    ],
    "name": "markAsDefaulted",
    "outputs": [],
    "stateMutability": "nonpayable",
    "type": "function"
  },
  {
    "inputs": [],
    "name": "owner",
    "outputs": [
      {
        "internalType": "address",
        "name": "",
        "type": "address"
      }
    ],
    "stateMutability": "view",
    "type": "function"
  },
  {
    "inputs": [
      {
        "internalType": "uint256",
        "name": "loanId",
        "type": "uint256"
      },
      {
        "internalType": "string",
        "name": "reason",
        "type": "string"
      }
    ],
    "name": "rejectLoan",
    "outputs": [],
    "stateMutability": "nonpayable",
    "type": "function"
  },
  {
    "inputs": [],
    "name": "renounceOwnership",
    "outputs": [],
    "stateMutability": "nonpayable",
    "type": "function"
  },
  {
    "inputs": [
      {
        "internalType": "uint256",
        "name": "loanId",
        "type": "uint256"
      }
    ],
    "name": "repayLoan",
    "outputs": [],
    "stateMutability": "payable",
    "type": "function"
  },
  {
    "inputs": [
      {
        "internalType": "uint256",
        "name": "tierId",
        "type": "uint256"
      },
      {
        "internalType": "uint256",
        "name": "amount",
        "type": "uint256"
      }
    ],
    "name": "requestLoan",
    "outputs": [],
    "stateMutability": "nonpayable",
    "type": "function"
  },
  {
    "inputs": [],
    "name": "tierCount",
    "outputs": [
      {
        "internalType": "uint256",
        "name": "",
        "type": "uint256"
      }
    ],
    "stateMutability": "view",
    "type": "function"
  },
  {
    "inputs": [],
    "name": "totalFunds",
    "outputs": [
      {
        "internalType": "uint256",
        "name": "",
        "type": "uint256"
      }
    ],
    "stateMutability": "view",
    "type": "function"
  },
  {
    "inputs": [
      {
        "internalType": "address",
        "name": "newOwner",
        "type": "address"
      }
    ],
    "name": "transferOwnership",
    "outputs": [],
    "stateMutability": "nonpayable",
    "type": "function"
  },
  {
    "inputs": [
      {
        "internalType": "uint256",
        "name": "tierId",
        "type": "uint256"
      },
      {
        "internalType": "string",
        "name": "name",
        "type": "string"
      },
      {
        "internalType": "uint256",
        "name": "minScore",
        "type": "uint256"
      },
      {
        "internalType": "uint256",
        "name": "maxAmount",
        "type": "uint256"
      },
      {
        "internalType": "uint256",
        "name": "interestRate",
        "type": "uint256"
      },
      {
        "internalType": "uint256",
        "name": "termMonths",
        "type": "uint256"
      },
      {
        "internalType": "bool",
        "name": "active",
        "type": "bool"
      }
    ],
    "name": "updateLoanTier",
    "outputs": [],
    "stateMutability": "nonpayable",
    "type": "function"
  },
  {
    "inputs": [
      {
        "internalType": "uint256",
        "name": "amount",
        "type": "uint256"
      }
    ],
    "name": "withdrawFunds",
    "outputs": [],
    "stateMutability": "nonpayable",
    "type": "function"
  },
  {
    "stateMutability": "payable",
    "type": "receive"
  }
]
